README.rst
setup.cfg
setup.py
veriocheck/__init__.py
veriocheck/veriocheck.py
veriocheck.egg-info/PKG-INFO
veriocheck.egg-info/SOURCES.txt
veriocheck.egg-info/dependency_links.txt
veriocheck.egg-info/top_level.txt