Metadata-Version: 1.1
Name: veriocheck
Version: 1.0.2
Summary: VerioCheck Contact Validation & Identity Verification API
Home-page: https://veriocheck.com
Author: VerioCheck
Author-email: info@veriocheck.com
License: MIT
Keywords: VerioCheck Address Validation Identity Verification Name Gender SMS Verification IP Reputation Check Email API
Platform: UNKNOWN
Classifier: Development Status :: 5 - Production/Stable
